take_confusion_matrix/__init__.py
take_confusion_matrix/calculation.py
take_confusion_matrix/validation.py
take_confusion_matrix/tests/__init__.py
take_confusion_matrix/tests/test_calculation.py
take_confusion_matrix/tests/test_validation.py
TakeConfusionMatrix-0.0.10.dist-info/LICENCE
TakeConfusionMatrix-0.0.10.dist-info/METADATA
TakeConfusionMatrix-0.0.10.dist-info/WHEEL
TakeConfusionMatrix-0.0.10.dist-info/top_level.txt
TakeConfusionMatrix-0.0.10.dist-info/RECORD
