Metadata-Version: 2.1
Name: TakeConfusionMatrix
Version: 0.0.10
Summary: TakeConfusionMatrix is a tool for batched metrics calculations
Home-page: https://curupira.visualstudio.com/DefaultCollection/Data%20Analytics%20%28DA%29/_git/TakeConfusionMatrix
Author: Cecília Assis
Author-email: cecilia.assis@take.net
Maintainer: D&A Team
Maintainer-email: analytics.ped@take.net
License: UNKNOWN
Platform: UNKNOWN
Classifier: Programming Language :: Python :: 3
Classifier: License :: OSI Approved :: MIT License
Classifier: Operating System :: OS Independent
Requires-Dist: pandas (>=1.0.4)
Requires-Dist: scikit-learn (>=0.23.1)
Requires-Dist: matplotlib (>=3.2.2)
Requires-Dist: seaborn (>=0.10.1)
